MANIFEST.in
README.md
requirements.txt
setup.py
django_mp_barcode.egg-info/PKG-INFO
django_mp_barcode.egg-info/SOURCES.txt
django_mp_barcode.egg-info/dependency_links.txt
django_mp_barcode.egg-info/requires.txt
django_mp_barcode.egg-info/top_level.txt
product_barcode/__init__.py
product_barcode/admin.py
product_barcode/filters.py
product_barcode/models.py
product_barcode/settings.py
product_barcode/tests.py
product_barcode/urls.py
product_barcode/utils.py
product_barcode/views.py
product_barcode/locale/uk/LC_MESSAGES/django.mo
product_barcode/locale/uk/LC_MESSAGES/django.po
product_barcode/migrations/0001_initial.py
product_barcode/migrations/__init__.py
product_barcode/templates/barcode/generate.html
product_barcode/templates/barcode/print.html