Metadata-Version: 2.1
Name: django-mp-barcode
Version: 1.1.0
Summary: Django barcode app
Home-page: https://github.com/pmaigutyak/mp-barcode
Author: Paul Maigutyak
Author-email: pmaigutyak@gmail.com
License: MIT
Download-URL: https://github.com/pmaigutyak/mp-barcode/archive/1.1.0.tar.gz
Platform: UNKNOWN
